Metadata-Version: 2.0
Name: django-jenkins
Version: 0.19.0
Summary: Plug and play continuous integration with django and jenkins
Home-page: http://github.com/kmmbvnr/django-jenkins
Author: Mikhail Podgurskiy
Author-email: kmmbvnr@gmail.com
License: LGPL
Keywords: pyunit,unittest,testrunner,hudson,jenkins,django,pylint,pep8,pyflakes,csslint,scsslint,jshint,coverage
Platform: Any
Classifier: Development Status :: 5 - Production/Stable
Classifier: Intended Audience :: Developers
Classifier: License :: OSI Approved :: GNU Library or Lesser General Public License (LGPL)
Classifier: Natural Language :: English
Classifier: Operating System :: OS Independent
Classifier: Framework :: Django
Classifier: Framework :: Django :: 1.8
Classifier: Framework :: Django :: 1.9
Classifier: Programming Language :: Python
Classifier: Programming Language :: Python :: 2.7
Classifier: Programming Language :: Python :: 3
Classifier: Programming Language :: Python :: 3.4
Classifier: Programming Language :: Python :: 3.5
Classifier: Topic :: Software Development :: Libraries :: Python Modules
Classifier: Topic :: Software Development :: Testing
Requires-Dist: Django (>=1.8)
